{
    "title": "Brewing a Cup of Coffee Ninja Coffee Bar System - Glass Carafe",
    "description": "No Voice! This is a SIMPLE How-to video..Watch how to use and brew a cup of coffee in the Ninja Coffee Bar System with this simple and straight forward video.",
    "referenceId": "ze4rI3tn4CM",
    "date_created": "1488570950",
    "date_modified": "1488855026",
    "tags": "How_to",
    "sourceId": "4",
    "VIDEO_LENGTH": "LONG",
    "status": "approved",
    "visibility": "1",
    "VV_VI": null,
    "CVV_VI": null,
    "engagement_score": null,
    "conversion_score": null,
    "id": "85667523",
    "loginId": "1758397",
    "entityType": "1",
    "titleTextEncoded": "Brewing-a-Cup-of-Coffee-Ninja-Coffee-Bar-System-Glass-Carafe",
    "category": null,
    "duration": 242,
    "settings": null,
    "asset": {
        "type": "youtube",
        "author": "JennyLeeBlogs",
        "hdvFlag": 1,
        "description": "No Voice! This is a SIMPLE How-to video..Watch how to use and brew a cup of coffee in the Ninja Coffee Bar System with this simple and straight forward video.",
        "tags": "",
        "thumbnailUrl": "https:\/\/i.ytimg.com\/vi\/ze4rI3tn4CM\/hqdefault.jpg",
        "videoId": "ze4rI3tn4CM",
        "mediaDuration": 242,
        "prettyDuration": "00:04:02",
        "uploadAsset": false,
        "quality": ""
    },
    "transcripts": null,
    "metrics_statistics": null,
    "tvp_profiles": null,
    "tvp_profiles_manual": null,
    "tvp_profiles_maxscore": null
}